Metadata-Version: 2.1
Name: conan-clang-update
Version: 0.3.0
Summary: Conan script to update Clang on Travis CI
Home-page: https://github.com/uilianries/conan-clang-update
Author: Uilian Ries
Author-email: uilianries@gmail.com
License: MIT
Keywords: conan,C/C++,package,libraries,developer,manager,dependency,tool,c,c++,cpp
Platform: UNKNOWN
Classifier: Development Status :: 4 - Beta
Classifier: Intended Audience :: Developers
Classifier: Topic :: Software Development :: Build Tools
Classifier: License :: OSI Approved :: MIT License
Classifier: Programming Language :: Python :: 2
Classifier: Programming Language :: Python :: 2.7
Classifier: Programming Language :: Python :: 3
Provides-Extra: test
